ynput/__init__.py
ynput-0.1.1.dist-info/METADATA
ynput-0.1.1.dist-info/WHEEL
ynput-0.1.1.dist-info/top_level.txt
ynput-0.1.1.dist-info/RECORD
