Metadata-Version: 2.1
Name: ynput
Version: 0.1.1
Summary: Ynput namespace
Author-email: Dee Coureau <dee@ynput.com>
Project-URL: Website, https://ynput.io
Project-URL: Githup, https://github.com/ynput
Provides-Extra: dev
Requires-Dist: build ; extra == 'dev'
Requires-Dist: twine ; extra == 'dev'
